dotshow/__init__.py
dotshow/matching.py
dotshow/under.py
dotshow/weight.py
dotshow-1.2.5.dist-info/LICENSE
dotshow-1.2.5.dist-info/METADATA
dotshow-1.2.5.dist-info/WHEEL
dotshow-1.2.5.dist-info/top_level.txt
dotshow-1.2.5.dist-info/RECORD
