Metadata-Version: 2.1
Name: dotshow
Version: 1.2.5
Summary: Drawing image on terminal
Home-page: https://github.com/kojunseo/dotshow
Author: kojunseo
Author-email: sta06167@naver.com
License: UNKNOWN
Platform: UNKNOWN
Classifier: License :: OSI Approved :: MIT License
License-File: LICENSE
Requires-Dist: opencv-python
Requires-Dist: numpy
